Metadata-Version: 2.1
Name: cashcat
Version: 1004
Summary: simple file integrity verification tool
Home-page: https://github.com/bitrate16/cashcat
Author: bitrate16
Author-email: bitrate16@gmail.com
License: AGPL-3
License-File: LICENSE
